kieli.py
kieli-1.2.2.dist-info/LICENSE
kieli-1.2.2.dist-info/WHEEL
kieli-1.2.2.dist-info/METADATA
kieli-1.2.2.dist-info/RECORD
