Metadata-Version: 2.1
Name: kieli
Version: 1.2.2
Summary: Minimalistic language server protocol client.
Home-page: https://github.com/PurpleMyst/kieli
License: UNKNOWN
Author: PurpleMyst
Author-email: PurpleMyst@users.noreply.github.com
Requires-Python: ~=3.4
Classifier: License :: OSI Approved :: MIT License
Requires-Dist: attrs
